{
    "keep": {
        "days": true,
        "amount": 14
    },
    "auditLog": "src\\log\\diagnosis\\.29bda40d6ff81c3fb4733a0899b967a34a6680d1-audit.json",
    "files": [
        {
            "date": 1679972732785,
            "name": "src\\log\\diagnosis\\diagnosis-2023-03-28.log",
            "hash": "dd3322b540dbdae342e5e8416e6701396aad4a0d12b6b0539e43789647984b71"
        },
        {
            "date": 1680074961565,
            "name": "src\\log\\diagnosis\\diagnosis-2023-03-29.log",
            "hash": "6ac1f538eb9a2ee9210b3f0e7ffb59b5aa80379f12bed64043eaff396190655b"
        },
        {
            "date": 1680143408105,
            "name": "src\\log\\diagnosis\\diagnosis-2023-03-30.log",
            "hash": "dba7fad96b5735bd442ccb7be4d59324a1d077336de59d94379461e32c311c2e"
        },
        {
            "date": 1680247679417,
            "name": "src\\log\\diagnosis\\diagnosis-2023-03-31.log",
            "hash": "043a20b1cee9d0370d698c3c520948e6843f8d3743b1ba5ea25abdf4bb84ae16"
        },
        {
            "date": 1680365348881,
            "name": "src\\log\\diagnosis\\diagnosis-2023-04-01.log",
            "hash": "a767787851c18568344ccb19b74141c152c3807cb6c0c19ee01e8beeb5038c95"
        },
        {
            "date": 1680368799329,
            "name": "src\\log\\diagnosis\\diagnosis-2023-04-02.log",
            "hash": "a337a706c99de7c6aff6fd5682202b58f67392fd01308627cbc24a46fc77fbea"
        },
        {
            "date": 1680494129833,
            "name": "src\\log\\diagnosis\\diagnosis-2023-04-03.log",
            "hash": "6e064d7512336ae94ba99d2b786be6be7c36bfc92a779aa0c8961a36707a1d0b"
        },
        {
            "date": 1680543435213,
            "name": "src\\log\\diagnosis\\diagnosis-2023-04-04.log",
            "hash": "aa6b4a7021d5945f48c84056ebdc3ca65c7817d0fad529dc92a3b99ceeddb805"
        },
        {
            "date": 1680628565000,
            "name": "src\\log\\diagnosis\\diagnosis-2023-04-05.log",
            "hash": "77337b95b8b7ba6b7e4ef2ecc3dfb3cee943ab4c3c8f6468e74c3fb741de9cec"
        },
        {
            "date": 1680723871303,
            "name": "src\\log\\diagnosis\\diagnosis-2023-04-06.log",
            "hash": "93062bfd393e8e4efe92ab3d7ae0fa774d4528c8b086104563e65c44b48a05e1"
        },
        {
            "date": 1680802083258,
            "name": "src\\log\\diagnosis\\diagnosis-2023-04-07.log",
            "hash": "3b76a63fd3540a7be9cecc44b7d6694e4abb5a90684eabb26da8715437ec5d63"
        },
        {
            "date": 1680945564823,
            "name": "src\\log\\diagnosis\\diagnosis-2023-04-08.log",
            "hash": "2b942e273d25dddd3e67a25e21da0a6c0fcf0c153c87d62e662ffa4c95194f75"
        },
        {
            "date": 1681007100186,
            "name": "src\\log\\diagnosis\\diagnosis-2023-04-09.log",
            "hash": "dee24554b4a93d59dc740de808cd13b65d74f0859d9a3a180bd9f67fe96b1601"
        },
        {
            "date": 1681067911035,
            "name": "src\\log\\diagnosis\\diagnosis-2023-04-10.log",
            "hash": "258cc6b860e3d80af2458f6d8721faca059ac97fc073e4085b2371b926fdf76a"
        }
    ],
    "hashType": "sha256"
}