{
    "keep": {
        "days": true,
        "amount": 14
    },
    "auditLog": "src\\log\\treatmentPlan\\.d87ce08e1f50a9e65ef805c1b882359f105e2aae-audit.json",
    "files": [
        {
            "date": 1677609524031,
            "name": "src\\log\\treatmentPlan\\treatmentPlan-2023-03-01.log",
            "hash": "1afefc94a726ad49a6fd3be6369beb4e647fe0769b2f8a35701184feba95894f"
        },
        {
            "date": 1677690005356,
            "name": "src\\log\\treatmentPlan\\treatmentPlan-2023-03-02.log",
            "hash": "b21eced061deda3f7630d74b235395c9e7e3f7025cd95827cbe89b8a7aa78408"
        },
        {
            "date": 1677777133486,
            "name": "src\\log\\treatmentPlan\\treatmentPlan-2023-03-03.log",
            "hash": "241ff6a2f1628562ab5b78077966580c13be18b96258dc0413ca153fe1f7ffe7"
        },
        {
            "date": 1677862834567,
            "name": "src\\log\\treatmentPlan\\treatmentPlan-2023-03-04.log",
            "hash": "b4b840e72115acc00d025daa4265f666dd79a0da8d78cd83f74077e39c4b4469"
        },
        {
            "date": 1677950842027,
            "name": "src\\log\\treatmentPlan\\treatmentPlan-2023-03-05.log",
            "hash": "01b087bef7912b9333798ac4ca3802c070db275482042941e05c8ce3f92c66f5"
        },
        {
            "date": 1678037342826,
            "name": "src\\log\\treatmentPlan\\treatmentPlan-2023-03-06.log",
            "hash": "d6e0e94b0332aa465f5f9edde9548a1cf8a989131d91729400ded8d131fd188f"
        }
    ],
    "hashType": "sha256"
}